django_enum_choices/__init__.py
django_enum_choices/__version__.py
django_enum_choices/admin.py
django_enum_choices/choice_builders.py
django_enum_choices/exceptions.py
django_enum_choices/fields.py
django_enum_choices/filters.py
django_enum_choices/forms.py
django_enum_choices/serializers.py
django_enum_choices/utils.py
django_enum_choices/validators.py
django_enum_choices/tests/__init__.py
django_enum_choices/tests/settings.py
django_enum_choices/tests/test_admin_filter.py
django_enum_choices/tests/test_filters.py
django_enum_choices/tests/test_filterset_integrations.py
django_enum_choices/tests/test_form_fields.py
django_enum_choices/tests/test_form_integrations.py
django_enum_choices/tests/test_model_fields.py
django_enum_choices/tests/test_model_integrations.py
django_enum_choices/tests/test_serializer_fields.py
django_enum_choices/tests/test_serializer_integrations.py
django_enum_choices/tests/e2e/tests.py
django_enum_choices/tests/e2e/e2e/manage.py
django_enum_choices/tests/e2e/e2e/e2e/__init__.py
django_enum_choices/tests/e2e/e2e/e2e/settings.py
django_enum_choices/tests/e2e/e2e/e2e/urls.py
django_enum_choices/tests/e2e/e2e/e2e/wsgi.py
django_enum_choices/tests/e2e/e2e/test_models/__init__.py
django_enum_choices/tests/e2e/e2e/test_models/admin.py
django_enum_choices/tests/e2e/e2e/test_models/apps.py
django_enum_choices/tests/e2e/e2e/test_models/models.py
django_enum_choices/tests/e2e/e2e/test_models/tests.py
django_enum_choices/tests/e2e/e2e/test_models/views.py
django_enum_choices/tests/e2e/e2e/test_models/migrations/0001_initial.py
django_enum_choices/tests/e2e/e2e/test_models/migrations/__init__.py
django_enum_choices/tests/testapp/apps.py
django_enum_choices/tests/testapp/database_routers.py
django_enum_choices/tests/testapp/enumerations.py
django_enum_choices/tests/testapp/models.py
django_enum_choices-2.1.4.dist-info/LICENSE
django_enum_choices-2.1.4.dist-info/METADATA
django_enum_choices-2.1.4.dist-info/WHEEL
django_enum_choices-2.1.4.dist-info/top_level.txt
django_enum_choices-2.1.4.dist-info/RECORD
