Metadata-Version: 2.1
Name: django-enum-choices
Version: 2.1.4
Summary: A custom Django field able to use subclasses of Python's internal `Enum` class as choices
Home-page: https://github.com/HackSoftware/django-enum-choices
Author: Vasil Slavov
Author-email: vasil.slavov@hacksoft.io
License: MIT
Platform: UNKNOWN
Classifier: License :: OSI Approved :: MIT License
Classifier: Programming Language :: Python
Classifier: Programming Language :: Python :: 3
Classifier: Programming Language :: Python :: 3.5
Classifier: Programming Language :: Python :: 3.6
Classifier: Programming Language :: Python :: 3.7
Classifier: Programming Language :: Python :: Implementation :: CPython
Classifier: Framework :: Django
Classifier: Framework :: Django :: 1.11
Classifier: Framework :: Django :: 2.1
Classifier: Framework :: Django :: 2.2
Classifier: Operating System :: OS Independent
Classifier: Intended Audience :: Developers
Classifier: Topic :: Software Development :: Libraries
Requires-Python: >=3.5.0
Provides-Extra: dev
